dataclass_as_data/__init__.py
dataclass_as_data/dataclass_as_data.py
dataclass_as_data/py.typed
tests/__init__.py
tests/test_dataclass_as_data.py
tests/test_dataclasses.py
dataclass_as_data-0.2.0.dist-info/LICENSE
dataclass_as_data-0.2.0.dist-info/METADATA
dataclass_as_data-0.2.0.dist-info/WHEEL
dataclass_as_data-0.2.0.dist-info/top_level.txt
dataclass_as_data-0.2.0.dist-info/RECORD
