Metadata-Version: 2.1
Name: dataclass-as-data
Version: 0.2.0
Summary: Simple configurable conversion of dataclasses to raw data
Home-page: https://gitlab.com/sigmath_bits/dataclass-as-data
Author: Sigmath Bits
License: GPLv3
Classifier: Development Status :: 4 - Beta
Classifier: License :: OSI Approved :: GNU General Public License v3 (GPLv3)
Classifier: Programming Language :: Python :: 3
Classifier: Programming Language :: Python :: 3 :: Only
Classifier: Programming Language :: Python :: 3.9
Classifier: Programming Language :: Python :: 3.10
Requires-Python: >=3.9
License-File: LICENSE
Provides-Extra: dev
Requires-Dist: tox (==4.0.5) ; extra == 'dev'
Requires-Dist: mypy (==0.991) ; extra == 'dev'
Requires-Dist: build (==0.7.0) ; extra == 'dev'
Requires-Dist: twine (==4.0.0) ; extra == 'dev'
Requires-Dist: typing-extensions (==4.4.0) ; extra == 'dev'
Provides-Extra: test
Requires-Dist: tox (==3.25.0) ; extra == 'test'
Requires-Dist: mypy (==0.991) ; extra == 'test'
Requires-Dist: typing-extensions (==4.4.0) ; extra == 'test'
